README.md
setup.py
leakyblobs/__init__.py
leakyblobs/leakyblobs.py
leakyblobs.egg-info/PKG-INFO
leakyblobs.egg-info/SOURCES.txt
leakyblobs.egg-info/dependency_links.txt
leakyblobs.egg-info/requires.txt
leakyblobs.egg-info/top_level.txt
tests/test_marjane_cluster_evaluator.py
tests/test_marjane_cluster_prediction.py